pyramid_debugtoolbar/__init__.py
pyramid_debugtoolbar/console.py
pyramid_debugtoolbar/repr.py
pyramid_debugtoolbar/tbtools.py
pyramid_debugtoolbar/toolbar.py
pyramid_debugtoolbar/toolbar_app.py
pyramid_debugtoolbar/utils.py
pyramid_debugtoolbar/panels/__init__.py
pyramid_debugtoolbar/panels/headers.py
pyramid_debugtoolbar/panels/introspection.py
pyramid_debugtoolbar/panels/logger.py
pyramid_debugtoolbar/panels/performance.py
pyramid_debugtoolbar/panels/renderings.py
pyramid_debugtoolbar/panels/request_vars.py
pyramid_debugtoolbar/panels/routes.py
pyramid_debugtoolbar/panels/session.py
pyramid_debugtoolbar/panels/settings.py
pyramid_debugtoolbar/panels/sqla.py
pyramid_debugtoolbar/panels/traceback.py
pyramid_debugtoolbar/panels/tweens.py
pyramid_debugtoolbar/panels/versions.py
pyramid_debugtoolbar/panels/templates/headers.dbtmako
pyramid_debugtoolbar/panels/templates/introspection.dbtmako
pyramid_debugtoolbar/panels/templates/logger.dbtmako
pyramid_debugtoolbar/panels/templates/performance.dbtmako
pyramid_debugtoolbar/panels/templates/renderings.dbtmako
pyramid_debugtoolbar/panels/templates/request_vars.dbtmako
pyramid_debugtoolbar/panels/templates/routes.dbtmako
pyramid_debugtoolbar/panels/templates/session.dbtmako
pyramid_debugtoolbar/panels/templates/settings.dbtmako
pyramid_debugtoolbar/panels/templates/sqlalchemy.dbtmako
pyramid_debugtoolbar/panels/templates/sqlalchemy_explain.dbtmako
pyramid_debugtoolbar/panels/templates/sqlalchemy_select.dbtmako
pyramid_debugtoolbar/panels/templates/traceback.dbtmako
pyramid_debugtoolbar/panels/templates/tweens.dbtmako
pyramid_debugtoolbar/panels/templates/versions.dbtmako
pyramid_debugtoolbar/static/bootstrap/css/bootstrap.min.css
pyramid_debugtoolbar/static/bootstrap/fonts/glyphicons-halflings-regular.eot
pyramid_debugtoolbar/static/bootstrap/fonts/glyphicons-halflings-regular.svg
pyramid_debugtoolbar/static/bootstrap/fonts/glyphicons-halflings-regular.ttf
pyramid_debugtoolbar-4.12.dist-info/LICENSE.txt
pyramid_debugtoolbar-4.12.dist-info/METADATA
pyramid_debugtoolbar-4.12.dist-info/WHEEL
pyramid_debugtoolbar-4.12.dist-info/top_level.txt
pyramid_debugtoolbar-4.12.dist-info/RECORD
