Metadata-Version: 2.1
Name: pyramid_debugtoolbar
Version: 4.12
Summary: A package which provides an interactive HTML debugger for Pyramid application development
Home-page: https://docs.pylonsproject.org/projects/pyramid-debugtoolbar/en/latest/
Author: Chris McDonough, Michael Merickel, Casey Duncan, Blaise Laflamme
Author-email: pylons-discuss@googlegroups.com
License: BSD
Keywords: wsgi,pylons,pyramid,transaction
Classifier: Intended Audience :: Developers
Classifier: Programming Language :: Python
Classifier: Programming Language :: Python :: 3
Classifier: Programming Language :: Python :: 3.7
Classifier: Programming Language :: Python :: 3.8
Classifier: Programming Language :: Python :: 3.9
Classifier: Programming Language :: Python :: 3.10
Classifier: Programming Language :: Python :: 3.11
Classifier: Programming Language :: Python :: 3.12
Classifier: Framework :: Pyramid
Classifier: Topic :: Internet :: WWW/HTTP :: WSGI
Classifier: License :: Repoze Public License
Requires-Python: >=3.7
License-File: LICENSE.txt
Requires-Dist: pyramid >=1.4
Requires-Dist: pyramid-mako >=0.3.1
Requires-Dist: Pygments
Requires-Dist: importlib-metadata ; python_version < "3.8"
Provides-Extra: docs
Requires-Dist: Sphinx >=1.7.5 ; extra == 'docs'
Requires-Dist: pylons-sphinx-themes >=0.3 ; extra == 'docs'
Provides-Extra: testing
Requires-Dist: WebTest ; extra == 'testing'
Requires-Dist: pytest ; extra == 'testing'
Requires-Dist: pytest-cov ; extra == 'testing'
Requires-Dist: sqlalchemy ; extra == 'testing'
Requires-Dist: webob ; extra == 'testing'
